<configuration>
  <!-- client configuration may be either flash/rtmp or html/empty -->
  <client type="flash" producerserver="rtmp" audiocodec="mp3" audiobitrate="128000" videocodec="flv" videobitrate="1024000"/>            
  
  <!--  backend configurations multiple -->
  <backends>
    <backend type="htsp">
      <server>192.168.0.34</server>
      <port>9982</port>
      <httpport>9981</httpport>
      <usernmame>hts</usernmame>
      <password>hts</password>
    </backend>    
    <!-- backend type="eyetv">
      <server>192.168.0.7</server>
      <port>2170</port>      
    </backend!-->
  </backends>
</configuration>
